netbox_cloud_pilot/__init__.py
netbox_cloud_pilot/constants.py
netbox_cloud_pilot/forms.py
netbox_cloud_pilot/iaas.py
netbox_cloud_pilot/models.py
netbox_cloud_pilot/navigation.py
netbox_cloud_pilot/nb_settings.py
netbox_cloud_pilot/tables.py
netbox_cloud_pilot/urls.py
netbox_cloud_pilot/utils.py
netbox_cloud_pilot/views.py
netbox_cloud_pilot/api/__init__.py
netbox_cloud_pilot/api/serializers.py
netbox_cloud_pilot/api/urls.py
netbox_cloud_pilot/api/views.py
netbox_cloud_pilot/migrations/0001_initial.py
netbox_cloud_pilot/migrations/__init__.py
netbox_cloud_pilot/templates/netbox_cloud_pilot/netboxconfiguration.html
netbox_cloud_pilot/templates/netbox_cloud_pilot/netboxdbbackup.html
netbox_cloud_pilot/templates/netbox_cloud_pilot/nodelogs.html
netbox_cloud_pilot/templates/netbox_cloud_pilot/plugin_disable.html
netbox_cloud_pilot/templates/netbox_cloud_pilot/plugin_enable.html
netbox_cloud_pilot/templates/netbox_cloud_pilot/plugin_uninstall.html
netbox_cloud_pilot/templates/netbox_cloud_pilot/plugins_store.html
netbox_cloud_pilot/templates/netbox_cloud_pilot/inc/env_info.html
netbox_cloud_pilot/templates/netbox_cloud_pilot/inc/env_node_groups.html
netbox_cloud_pilot/templates/netbox_cloud_pilot/inc/plugin_store.html
netbox_cloud_pilot-0.1.21.dist-info/METADATA
netbox_cloud_pilot-0.1.21.dist-info/WHEEL
netbox_cloud_pilot-0.1.21.dist-info/top_level.txt
netbox_cloud_pilot-0.1.21.dist-info/RECORD
