Metadata-Version: 2.1
Name: netbox-cloud-pilot
Version: 0.1.21
Summary: Enhances NetBox on CloudMyDC's VAP with advanced management and control features.
Home-page: https://github.com/Onemind-Services-LLC/netbox-cloud-pilot/
Download-URL: https://github.com/Onemind-Services-LLC/netbox-cloud-pilot/
Author: Abhimanyu Saharan
Author-email: asaharan@onemindservices.com
Maintainer: Abhimanyu Saharan
Maintainer-email: asaharan@onemindservices.com
Keywords: netbox,netbox-plugin
Classifier: Development Status :: 3 - Alpha
Classifier: Framework :: Django
Classifier: Programming Language :: Python :: 3
Requires-Dist: py-jelastic
Requires-Dist: croniter <3.0.0
Requires-Dist: semver <4.0.0
Requires-Dist: requirements-parser
